marlin_pytorch/__init__.py
marlin_pytorch/config.py
marlin_pytorch/face_detector.py
marlin_pytorch/util.py
marlin_pytorch/version.txt
marlin_pytorch/model/__init__.py
marlin_pytorch/model/decoder.py
marlin_pytorch/model/encoder.py
marlin_pytorch/model/marlin.py
marlin_pytorch/model/modules.py
marlin_pytorch/model/positional_embedding.py
marlin_pytorch-0.3.4.dist-info/LICENSE
marlin_pytorch-0.3.4.dist-info/METADATA
marlin_pytorch-0.3.4.dist-info/WHEEL
marlin_pytorch-0.3.4.dist-info/top_level.txt
marlin_pytorch-0.3.4.dist-info/RECORD
