Metadata-Version: 2.1
Name: marlin-pytorch
Version: 0.3.4
Summary: Official pytorch implementation for MARLIN.
Home-page: https://github.com/ControlNet/MARLIN
Author: ControlNet
Author-email: smczx@hotmail.com
License: CC BY-NC 4.0
Project-URL: Bug Tracker, https://github.com/ControlNet/MARLIN/issues
Project-URL: Source Code, https://github.com/ControlNet/MARLIN
Keywords: deep learning,pytorch,AI
Platform: UNKNOWN
Classifier: Programming Language :: Python :: 3
Classifier: Programming Language :: Python :: 3.6
Classifier: Programming Language :: Python :: 3.7
Classifier: Programming Language :: Python :: 3.8
Classifier: Programming Language :: Python :: 3.9
Classifier: Programming Language :: Python :: 3.10
Classifier: License :: Other/Proprietary License
Classifier: Operating System :: OS Independent
Classifier: Intended Audience :: Developers
Classifier: Topic :: Scientific/Engineering :: Artificial Intelligence
Classifier: Topic :: Multimedia :: Video
Requires-Python: >=3.6
License-File: LICENSE
Requires-Dist: torch >=1.8.0
Requires-Dist: torchvision >=0.9.0
Requires-Dist: numpy >=1.10
Requires-Dist: einops >=0.1
Requires-Dist: ffmpeg-python >=0.2.0
Requires-Dist: opencv-python >=4.3
Requires-Dist: av >=6.0
Requires-Dist: tqdm >=4.0
Requires-Dist: pyyaml >=5.0
